tendril_monitor_vcs-0.1.0.dist-info/DESCRIPTION.rst
tendril_monitor_vcs-0.1.0.dist-info/METADATA
tendril_monitor_vcs-0.1.0.dist-info/RECORD
tendril_monitor_vcs-0.1.0.dist-info/WHEEL
tendril_monitor_vcs-0.1.0.dist-info/metadata.json
tendril_monitor_vcs-0.1.0.dist-info/top_level.txt
vcs_monitor/__init__.py
vcs_monitor/hook_post_commit.py
vcs_monitor/worker.py
