Metadata-Version: 2.0
Name: tendril-monitor-vcs
Version: 0.1.0
Summary: VCS monitoring and documentation generation server using Twisted for Tendril
Home-page: https://github.com/chintal/tendril-monitor-vcs
Author: Chintalagiri Shashank
Author-email: shashank@chintal.in
License: MIT
Keywords: tendril-monitor-vcs
Platform: UNKNOWN
Classifier: Development Status :: 4 - Beta
Classifier: License :: OSI Approved :: MIT License
Classifier: Natural Language :: English
Classifier: Programming Language :: Python
Requires-Dist: checkoutmanager
Requires-Dist: pika
Requires-Dist: twisted
